[
    {
        "inputs": [
            {
                "internalType": "string",
                "name": "erc20Name",
                "type": "string"
            },
            {
                "internalType": "string",
                "name": "erc20Symbol",
                "type": "string"
            },
            {
                "internalType": "uint256",
                "name": "_exchangeRatio",
                "type": "uint256"
            }
        ],
        "stateMutability": "nonpayable",
        "type": "constructor"
    },
    {
        "inputs": [],
        "name": "buy",
        "outputs": [],
        "stateMutability": "payable",
        "type": "function"
    },
    {
        "inputs": [
            {
                "internalType": "address",
                "name": "to",
                "type": "address"
            }
        ],
        "name": "buyTo",
        "outputs": [],
        "stateMutability": "payable",
        "type": "function"
    },
    {
        "inputs": [],
        "name": "erc20Lock",
        "outputs": [
            {
                "internalType": "contract ERC20Lock",
                "name": "",
                "type": "address"
            }
        ],
        "stateMutability": "view",
        "type": "function"
    },
    {
        "inputs": [],
        "name": "exchangeRatio",
        "outputs": [
            {
                "internalType": "uint256",
                "name": "",
                "type": "uint256"
            }
        ],
        "stateMutability": "view",
        "type": "function"
    },
    {
        "inputs": [
            {
                "internalType": "uint256",
                "name": "amount",
                "type": "uint256"
            }
        ],
        "name": "sell",
        "outputs": [],
        "stateMutability": "nonpayable",
        "type": "function"
    },
    {
        "inputs": [
            {
                "internalType": "address",
                "name": "to",
                "type": "address"
            },
            {
                "internalType": "uint256",
                "name": "amount",
                "type": "uint256"
            }
        ],
        "name": "sellTo",
        "outputs": [],
        "stateMutability": "nonpayable",
        "type": "function"
    }
]